{"book":"psalms","abbr":"PSA","chapter":98,"duration":27.434,"verses":[{"verse":1,"start":0.0,"end":2.6,"words":[{"word":"Sing","start":0.3,"end":0.82},{"word":"to","start":0.82,"end":1.08},{"word":"Yahweh","start":1.08,"end":1.54},{"word":"a","start":1.54,"end":1.72},{"word":"new","start":1.72,"end":1.9},{"word":"song,","start":1.9,"end":2.22}]},{"verse":2,"start":2.6,"end":5.757,"words":[{"word":"Yahweh","start":2.62,"end":3.46},{"word":"has","start":3.46,"end":3.74},{"word":"made","start":3.74,"end":3.94},{"word":"known","start":3.94,"end":4.22},{"word":"his","start":4.22,"end":4.48},{"word":"salvation.","start":4.48,"end":4.98}]},{"verse":3,"start":5.757,"end":11.218,"words":[{"word":"He","start":5.967,"end":6.447},{"word":"has","start":6.447,"end":6.647},{"word":"remembered","start":6.647,"end":7.007},{"word":"his","start":7.007,"end":7.227},{"word":"loving","start":7.227,"end":7.527},{"word":"kindness","start":7.527,"end":8.147},{"word":"and","start":8.147,"end":8.867},{"word":"his","start":8.867,"end":9.007},{"word":"faithfulness","start":9.007,"end":9.707},{"word":"toward","start":9.707,"end":9.967},{"word":"the","start":9.967,"end":10.287},{"word":"house","start":10.287,"end":10.527},{"word":"of","start":10.527,"end":10.707},{"word":"Israel.","start":10.707,"end":10.927}]},{"verse":4,"start":11.218,"end":14.674,"words":[{"word":"Make","start":11.428,"end":11.968},{"word":"a","start":11.968,"end":12.108},{"word":"joyful","start":12.108,"end":12.488},{"word":"noise","start":12.488,"end":12.908},{"word":"to","start":12.908,"end":13.168},{"word":"Yahweh,","start":13.168,"end":13.648},{"word":"all","start":13.648,"end":14.068},{"word":"the","start":14.068,"end":14.248},{"word":"earth!","start":14.248,"end":14.468}]},{"verse":5,"start":14.674,"end":17.877,"words":[{"word":"Sing","start":14.974,"end":15.494},{"word":"praises","start":15.494,"end":16.054},{"word":"to","start":16.054,"end":16.314},{"word":"Yahweh","start":16.314,"end":16.854},{"word":"with","start":16.854,"end":17.094},{"word":"the","start":17.094,"end":17.214},{"word":"harp,","start":17.214,"end":17.454}]},{"verse":6,"start":17.877,"end":20.779,"words":[{"word":"With","start":17.877,"end":18.317},{"word":"trumpets","start":18.317,"end":18.897},{"word":"and","start":18.897,"end":19.037},{"word":"sound","start":19.037,"end":19.417},{"word":"of","start":19.417,"end":19.597},{"word":"the","start":19.597,"end":19.697},{"word":"ram's","start":19.697,"end":20.097},{"word":"horn,","start":20.097,"end":20.337}]},{"verse":7,"start":20.779,"end":23.168,"words":[{"word":"Let","start":20.829,"end":21.369},{"word":"the","start":21.369,"end":21.569},{"word":"sea","start":21.569,"end":21.809},{"word":"roar","start":21.809,"end":22.109},{"word":"with","start":22.109,"end":22.369},{"word":"its","start":22.369,"end":22.529},{"word":"fullness;","start":22.529,"end":22.829}]},{"verse":8,"start":23.168,"end":25.472,"words":[{"word":"Let","start":23.168,"end":23.668},{"word":"the","start":23.668,"end":23.868},{"word":"rivers","start":23.868,"end":24.088},{"word":"clap","start":24.088,"end":24.508},{"word":"their","start":24.508,"end":24.848},{"word":"hands.","start":24.848,"end":25.208}]},{"verse":9,"start":25.472,"end":27.434,"words":[{"word":"Let","start":25.472,"end":25.832},{"word":"them","start":25.832,"end":26.072},{"word":"sing","start":26.072,"end":26.412},{"word":"before","start":26.412,"end":26.772},{"word":"Yahweh,","start":26.772,"end":27.332}]}]}