{"book":"acts","abbr":"ACT","chapter":15,"duration":270.238,"verses":[{"verse":1,"start":0.0,"end":9.295,"words":[{"word":"Some","start":0.27,"end":0.79},{"word":"men","start":0.79,"end":1.05},{"word":"came","start":1.05,"end":1.31},{"word":"down","start":1.31,"end":1.63},{"word":"from","start":1.63,"end":1.89},{"word":"Judea","start":1.89,"end":2.47},{"word":"and","start":2.47,"end":2.63},{"word":"taught","start":2.63,"end":2.91},{"word":"the","start":2.91,"end":3.09},{"word":"brothers,","start":3.09,"end":3.41},{"word":"\"Unless","start":3.41,"end":4.43},{"word":"you","start":4.43,"end":4.79},{"word":"are","start":4.79,"end":4.97},{"word":"circumcised","start":4.97,"end":5.79},{"word":"after","start":5.79,"end":6.13},{"word":"the","start":6.13,"end":6.31},{"word":"custom","start":6.31,"end":6.67},{"word":"of","start":6.67,"end":6.87},{"word":"Moses,","start":6.87,"end":7.21},{"word":"you","start":7.21,"end":8.05},{"word":"can't","start":8.05,"end":8.47},{"word":"be","start":8.47,"end":8.59},{"word":"saved.\"","start":8.59,"end":8.97}]},{"verse":2,"start":9.295,"end":23.76,"words":[{"word":"Therefore","start":9.505,"end":10.205},{"word":"when","start":10.385,"end":10.525},{"word":"Paul","start":10.525,"end":10.905},{"word":"and","start":10.905,"end":11.065},{"word":"Barnabas","start":11.065,"end":11.725},{"word":"had","start":11.725,"end":12.085},{"word":"no","start":12.085,"end":12.325},{"word":"small","start":12.325,"end":12.705},{"word":"discord","start":12.705,"end":13.125},{"word":"and","start":13.125,"end":13.425},{"word":"discussion","start":13.425,"end":13.845},{"word":"with","start":13.845,"end":14.165},{"word":"them,","start":14.165,"end":14.405},{"word":"they","start":14.685,"end":14.845},{"word":"appointed","start":14.845,"end":15.285},{"word":"Paul,","start":15.285,"end":15.825},{"word":"Barnabas,","start":16.425,"end":17.025},{"word":"and","start":17.325,"end":17.745},{"word":"some","start":17.745,"end":17.985},{"word":"others","start":17.985,"end":18.265},{"word":"of","start":18.265,"end":18.505},{"word":"them","start":18.505,"end":18.705},{"word":"to","start":18.705,"end":18.905},{"word":"go","start":18.905,"end":19.065},{"word":"up","start":19.065,"end":19.245},{"word":"to","start":19.245,"end":19.445},{"word":"Jerusalem","start":19.445,"end":20.165},{"word":"to","start":20.165,"end":21.025},{"word":"the","start":21.025,"end":21.185},{"word":"apostles","start":21.185,"end":21.585},{"word":"and","start":21.585,"end":22.065},{"word":"elders","start":22.065,"end":22.405},{"word":"about","start":22.405,"end":22.825},{"word":"this","start":22.825,"end":23.145},{"word":"question.","start":23.145,"end":23.525}]},{"verse":3,"start":23.76,"end":36.294,"words":[{"word":"They,","start":24.0,"end":24.6},{"word":"being","start":24.78,"end":25.2},{"word":"sent","start":25.2,"end":25.54},{"word":"on","start":25.54,"end":25.78},{"word":"their","start":25.78,"end":25.98},{"word":"way","start":25.98,"end":26.18},{"word":"by","start":26.18,"end":26.4},{"word":"the","start":26.4,"end":26.56},{"word":"assembly,","start":26.56,"end":27.02},{"word":"passed","start":27.66,"end":28.0},{"word":"through","start":28.0,"end":28.4},{"word":"both","start":28.4,"end":28.66},{"word":"Phoenicia","start":28.66,"end":29.28},{"word":"and","start":29.28,"end":29.52},{"word":"Samaria,","start":29.52,"end":30.1},{"word":"declaring","start":30.76,"end":31.16},{"word":"the","start":31.16,"end":31.52},{"word":"conversion","start":31.52,"end":32.02},{"word":"of","start":32.02,"end":32.28},{"word":"the","start":32.28,"end":32.4},{"word":"Gentiles.","start":32.4,"end":33.16},{"word":"They","start":33.9,"end":34.04},{"word":"caused","start":34.04,"end":34.36},{"word":"great","start":34.36,"end":34.66},{"word":"joy","start":34.66,"end":35.0},{"word":"to","start":35.0,"end":35.26},{"word":"all","start":35.26,"end":35.54},{"word":"the","start":35.54,"end":35.72},{"word":"brothers.","start":35.72,"end":36.0}]},{"verse":4,"start":36.294,"end":46.62,"words":[{"word":"When","start":36.794,"end":37.054},{"word":"they","start":37.054,"end":37.294},{"word":"had","start":37.294,"end":37.494},{"word":"come","start":37.494,"end":37.714},{"word":"to","start":37.714,"end":37.854},{"word":"Jerusalem,","start":37.854,"end":38.434},{"word":"they","start":38.954,"end":39.174},{"word":"were","start":39.174,"end":39.314},{"word":"received","start":39.314,"end":39.674},{"word":"by","start":39.674,"end":39.974},{"word":"the","start":39.974,"end":40.134},{"word":"assembly","start":40.134,"end":40.614},{"word":"and","start":40.614,"end":41.434},{"word":"the","start":41.434,"end":41.554},{"word":"apostles","start":41.554,"end":41.974},{"word":"and","start":41.974,"end":42.394},{"word":"the","start":42.394,"end":42.534},{"word":"elders,","start":42.534,"end":42.834},{"word":"and","start":43.664,"end":43.864},{"word":"they","start":43.864,"end":44.004},{"word":"reported","start":44.004,"end":44.464},{"word":"everything","start":44.464,"end":45.004},{"word":"that","start":45.004,"end":45.364},{"word":"God","start":45.364,"end":45.604},{"word":"had","start":45.604,"end":45.824},{"word":"done","start":45.824,"end":46.084},{"word":"with","start":46.084,"end":46.324},{"word":"them.","start":46.324,"end":46.524}]},{"verse":5,"start":46.62,"end":57.289,"words":[{"word":"But","start":46.86,"end":47.3},{"word":"some","start":47.3,"end":47.6},{"word":"of","start":47.6,"end":47.72},{"word":"the","start":47.72,"end":47.84},{"word":"sect","start":47.84,"end":48.08},{"word":"of","start":48.08,"end":48.26},{"word":"the","start":48.26,"end":48.36},{"word":"Pharisees","start":48.36,"end":49.18},{"word":"who","start":49.18,"end":49.32},{"word":"believed","start":49.32,"end":49.7},{"word":"rose","start":49.7,"end":50.08},{"word":"up,","start":50.08,"end":50.46},{"word":"saying,","start":50.88,"end":51.18},{"word":"\"It","start":51.92,"end":52.16},{"word":"is","start":52.16,"end":52.38},{"word":"necessary","start":52.38,"end":53.0},{"word":"to","start":53.0,"end":53.24},{"word":"circumcise","start":53.24,"end":53.96},{"word":"them,","start":53.96,"end":54.24},{"word":"and","start":54.24,"end":54.88},{"word":"to","start":54.88,"end":55.02},{"word":"command","start":55.02,"end":55.3},{"word":"them","start":55.3,"end":55.58},{"word":"to","start":55.58,"end":55.74},{"word":"keep","start":55.74,"end":55.94},{"word":"the","start":55.94,"end":56.14},{"word":"law","start":56.14,"end":56.44},{"word":"of","start":56.44,"end":56.62},{"word":"Moses.\"","start":56.62,"end":56.96}]},{"verse":6,"start":57.289,"end":62.184,"words":[{"word":"The","start":57.499,"end":57.979},{"word":"apostles","start":57.979,"end":58.379},{"word":"and","start":58.379,"end":58.739},{"word":"the","start":58.739,"end":58.879},{"word":"elders","start":58.879,"end":59.159},{"word":"were","start":59.159,"end":59.459},{"word":"gathered","start":59.459,"end":59.779},{"word":"together","start":59.779,"end":60.259},{"word":"to","start":60.259,"end":60.979},{"word":"see","start":60.979,"end":61.219},{"word":"about","start":61.219,"end":61.459},{"word":"this","start":61.459,"end":61.739},{"word":"matter.","start":61.739,"end":62.039}]},{"verse":7,"start":62.184,"end":77.775,"words":[{"word":"When","start":62.424,"end":62.964},{"word":"there","start":62.964,"end":63.244},{"word":"had","start":63.244,"end":63.424},{"word":"been","start":63.424,"end":63.584},{"word":"much","start":63.584,"end":63.864},{"word":"discussion,","start":63.864,"end":64.504},{"word":"Peter","start":64.864,"end":65.244},{"word":"rose","start":65.244,"end":65.604},{"word":"up","start":65.604,"end":65.884},{"word":"and","start":65.884,"end":66.064},{"word":"said","start":66.064,"end":66.304},{"word":"to","start":66.304,"end":66.484},{"word":"them,","start":66.484,"end":66.744},{"word":"\"Brothers,","start":67.324,"end":67.644},{"word":"you","start":68.384,"end":68.604},{"word":"know","start":68.604,"end":68.924},{"word":"that","start":68.924,"end":69.244},{"word":"a","start":69.244,"end":69.364},{"word":"good","start":69.364,"end":69.604},{"word":"while","start":69.604,"end":69.964},{"word":"ago","start":69.964,"end":70.284},{"word":"God","start":70.284,"end":70.884},{"word":"made","start":70.884,"end":71.744},{"word":"a","start":71.744,"end":71.904},{"word":"choice","start":71.904,"end":72.204},{"word":"among","start":72.204,"end":72.524},{"word":"you","start":72.524,"end":72.804},{"word":"that","start":72.804,"end":72.984},{"word":"by","start":72.984,"end":73.264},{"word":"my","start":73.264,"end":73.504},{"word":"mouth","start":73.504,"end":73.864},{"word":"the","start":73.864,"end":74.104},{"word":"nations","start":74.104,"end":74.584},{"word":"should","start":74.584,"end":75.124},{"word":"hear","start":75.124,"end":75.404},{"word":"the","start":75.404,"end":75.644},{"word":"word","start":75.644,"end":75.884},{"word":"of","start":75.884,"end":76.084},{"word":"the","start":76.084,"end":76.204},{"word":"Good","start":76.204,"end":76.424},{"word":"News","start":76.424,"end":76.784},{"word":"and","start":76.784,"end":77.044},{"word":"believe.","start":77.044,"end":77.404}]},{"verse":8,"start":77.775,"end":85.213,"words":[{"word":"God,","start":78.075,"end":78.735},{"word":"who","start":79.075,"end":79.215},{"word":"knows","start":79.215,"end":79.435},{"word":"the","start":79.435,"end":79.675},{"word":"heart,","start":79.675,"end":79.975},{"word":"testified","start":80.215,"end":80.475},{"word":"about","start":80.475,"end":80.975},{"word":"them,","start":80.975,"end":81.295},{"word":"giving","start":81.835,"end":82.055},{"word":"them","start":82.055,"end":82.335},{"word":"the","start":82.335,"end":82.475},{"word":"Holy","start":82.475,"end":82.715},{"word":"Spirit,","start":82.715,"end":83.315},{"word":"just","start":83.775,"end":84.115},{"word":"like","start":84.115,"end":84.415},{"word":"he","start":84.415,"end":84.575},{"word":"did","start":84.575,"end":84.735},{"word":"to","start":84.735,"end":84.915},{"word":"us.","start":84.915,"end":85.075}]},{"verse":9,"start":85.213,"end":90.899,"words":[{"word":"He","start":85.423,"end":85.903},{"word":"made","start":85.903,"end":86.163},{"word":"no","start":86.163,"end":86.463},{"word":"distinction","start":86.463,"end":86.983},{"word":"between","start":86.983,"end":87.423},{"word":"us","start":87.423,"end":87.863},{"word":"and","start":87.863,"end":88.103},{"word":"them,","start":88.103,"end":88.323},{"word":"cleansing","start":88.763,"end":89.323},{"word":"their","start":89.323,"end":89.663},{"word":"hearts","start":89.663,"end":90.023},{"word":"by","start":90.023,"end":90.383},{"word":"faith.","start":90.383,"end":90.663}]},{"verse":10,"start":90.899,"end":101.14,"words":[{"word":"Now","start":91.199,"end":91.699},{"word":"therefore","start":91.699,"end":92.259},{"word":"why","start":92.379,"end":92.719},{"word":"do","start":92.719,"end":92.959},{"word":"you","start":92.959,"end":93.099},{"word":"tempt","start":93.099,"end":93.419},{"word":"God,","start":93.419,"end":93.759},{"word":"that","start":94.379,"end":94.579},{"word":"you","start":94.579,"end":94.759},{"word":"should","start":94.759,"end":94.959},{"word":"put","start":94.959,"end":95.159},{"word":"a","start":95.159,"end":95.339},{"word":"yoke","start":95.339,"end":95.639},{"word":"on","start":95.639,"end":95.799},{"word":"the","start":95.799,"end":95.919},{"word":"neck","start":95.919,"end":96.119},{"word":"of","start":96.119,"end":96.299},{"word":"the","start":96.299,"end":96.419},{"word":"disciples","start":96.419,"end":96.959},{"word":"which","start":97.499,"end":97.639},{"word":"neither","start":97.639,"end":97.979},{"word":"our","start":97.979,"end":98.259},{"word":"fathers","start":98.259,"end":98.699},{"word":"nor","start":99.479,"end":99.719},{"word":"we","start":99.719,"end":99.999},{"word":"were","start":99.999,"end":100.199},{"word":"able","start":100.199,"end":100.399},{"word":"to","start":100.399,"end":100.619},{"word":"bear?","start":100.619,"end":100.899}]},{"verse":11,"start":101.14,"end":107.559,"words":[{"word":"But","start":101.51,"end":101.85},{"word":"we","start":101.85,"end":102.05},{"word":"believe","start":102.05,"end":102.47},{"word":"that","start":102.47,"end":102.73},{"word":"we","start":102.73,"end":102.91},{"word":"are","start":102.91,"end":103.09},{"word":"saved","start":103.09,"end":103.57},{"word":"through","start":103.57,"end":103.91},{"word":"the","start":103.91,"end":104.09},{"word":"grace","start":104.09,"end":104.45},{"word":"of","start":104.45,"end":104.65},{"word":"the","start":104.65,"end":104.77},{"word":"Lord","start":104.77,"end":105.01},{"word":"Jesus,","start":105.01,"end":105.61},{"word":"just","start":106.29,"end":106.55},{"word":"as","start":106.55,"end":106.87},{"word":"they","start":106.87,"end":107.07},{"word":"are.\"","start":107.07,"end":107.37}]},{"verse":12,"start":107.559,"end":117.855,"words":[{"word":"All","start":107.769,"end":108.369},{"word":"the","start":108.369,"end":108.569},{"word":"multitude","start":108.569,"end":108.989},{"word":"kept","start":108.989,"end":109.409},{"word":"silence,","start":109.409,"end":109.929},{"word":"and","start":110.729,"end":110.929},{"word":"they","start":110.929,"end":111.049},{"word":"listened","start":111.049,"end":111.489},{"word":"to","start":111.489,"end":111.709},{"word":"Barnabas","start":111.709,"end":112.509},{"word":"and","start":112.509,"end":112.669},{"word":"Paul","start":112.669,"end":113.049},{"word":"reporting","start":113.049,"end":113.709},{"word":"what","start":113.709,"end":114.089},{"word":"signs","start":114.089,"end":114.569},{"word":"and","start":114.569,"end":114.889},{"word":"wonders","start":114.889,"end":115.229},{"word":"God","start":115.229,"end":115.649},{"word":"had","start":115.649,"end":116.129},{"word":"done","start":116.129,"end":116.369},{"word":"among","start":116.369,"end":116.589},{"word":"the","start":116.589,"end":116.889},{"word":"nations","start":116.889,"end":117.269},{"word":"through","start":117.269,"end":117.629},{"word":"them.","start":117.629,"end":117.829}]},{"verse":13,"start":117.855,"end":122.783,"words":[{"word":"After","start":118.225,"end":118.625},{"word":"they","start":118.625,"end":118.825},{"word":"were","start":118.825,"end":118.965},{"word":"silent,","start":118.965,"end":119.405},{"word":"James","start":119.805,"end":120.045},{"word":"answered,","start":120.045,"end":120.585},{"word":"\"Brothers,","start":121.005,"end":121.385},{"word":"listen","start":121.925,"end":122.185},{"word":"to","start":122.185,"end":122.445},{"word":"me.","start":122.445,"end":122.625}]},{"verse":14,"start":122.783,"end":129.746,"words":[{"word":"Simeon","start":123.123,"end":123.923},{"word":"has","start":123.923,"end":124.123},{"word":"reported","start":124.123,"end":124.603},{"word":"how","start":124.603,"end":124.923},{"word":"God","start":124.923,"end":125.203},{"word":"first","start":125.203,"end":125.643},{"word":"visited","start":125.643,"end":126.283},{"word":"the","start":126.283,"end":126.683},{"word":"nations","start":126.683,"end":127.103},{"word":"to","start":127.103,"end":127.443},{"word":"take","start":127.443,"end":127.723},{"word":"out","start":127.723,"end":127.963},{"word":"of","start":127.963,"end":128.123},{"word":"them","start":128.123,"end":128.303},{"word":"a","start":128.303,"end":128.423},{"word":"people","start":128.423,"end":128.743},{"word":"for","start":128.743,"end":129.003},{"word":"his","start":129.003,"end":129.203},{"word":"name.","start":129.203,"end":129.463}]},{"verse":15,"start":129.746,"end":134.004,"words":[{"word":"This","start":129.986,"end":130.486},{"word":"agrees","start":130.486,"end":130.826},{"word":"with","start":130.826,"end":131.086},{"word":"the","start":131.086,"end":131.186},{"word":"words","start":131.186,"end":131.446},{"word":"of","start":131.446,"end":131.646},{"word":"the","start":131.646,"end":131.746},{"word":"prophets.","start":131.746,"end":132.166},{"word":"As","start":132.896,"end":133.216},{"word":"it","start":133.216,"end":133.356},{"word":"is","start":133.356,"end":133.536},{"word":"written,","start":133.536,"end":133.796}]},{"verse":16,"start":134.004,"end":136.826,"words":[{"word":"'After","start":134.504,"end":134.904},{"word":"these","start":134.904,"end":135.124},{"word":"things","start":135.124,"end":135.484},{"word":"I","start":135.484,"end":135.744},{"word":"will","start":135.744,"end":135.924},{"word":"return.","start":135.924,"end":136.264}]},{"verse":17,"start":136.826,"end":139.851,"words":[{"word":"that","start":137.066,"end":137.526},{"word":"the","start":137.526,"end":137.666},{"word":"rest","start":137.666,"end":137.926},{"word":"of","start":137.926,"end":138.086},{"word":"men","start":138.086,"end":138.326},{"word":"may","start":138.326,"end":138.546},{"word":"seek","start":138.546,"end":138.826},{"word":"after","start":138.826,"end":139.186},{"word":"the","start":139.186,"end":139.366},{"word":"Lord:","start":139.366,"end":139.626}]},{"verse":18,"start":139.851,"end":143.284,"words":[{"word":"\"All","start":140.281,"end":140.661},{"word":"of","start":140.661,"end":140.801},{"word":"God's","start":140.801,"end":141.221},{"word":"works","start":141.221,"end":141.561},{"word":"are","start":141.561,"end":141.821},{"word":"known","start":141.821,"end":142.001},{"word":"to","start":142.001,"end":142.221},{"word":"him","start":142.221,"end":142.381},{"word":"from","start":142.381,"end":142.561},{"word":"eternity.","start":142.561,"end":142.801}]},{"verse":19,"start":143.284,"end":149.692,"words":[{"word":"Therefore","start":143.524,"end":144.164},{"word":"my","start":144.164,"end":144.484},{"word":"judgment","start":144.484,"end":144.904},{"word":"is","start":144.904,"end":145.744},{"word":"that","start":145.744,"end":145.944},{"word":"we","start":145.944,"end":146.084},{"word":"don't","start":146.084,"end":146.424},{"word":"trouble","start":146.424,"end":146.724},{"word":"those","start":146.724,"end":147.044},{"word":"from","start":147.044,"end":147.324},{"word":"among","start":147.324,"end":147.544},{"word":"the","start":147.544,"end":147.764},{"word":"Gentiles","start":147.764,"end":148.404},{"word":"who","start":148.404,"end":148.624},{"word":"turn","start":148.624,"end":148.944},{"word":"to","start":148.944,"end":149.184},{"word":"God,","start":149.184,"end":149.444}]},{"verse":20,"start":149.692,"end":159.358,"words":[{"word":"but","start":150.032,"end":150.372},{"word":"that","start":150.372,"end":150.532},{"word":"we","start":150.532,"end":150.692},{"word":"write","start":150.692,"end":150.932},{"word":"to","start":150.932,"end":151.152},{"word":"them","start":151.152,"end":151.392},{"word":"that","start":151.392,"end":152.192},{"word":"they","start":152.192,"end":152.392},{"word":"abstain","start":152.392,"end":153.012},{"word":"from","start":153.012,"end":153.212},{"word":"the","start":153.212,"end":153.352},{"word":"pollution","start":153.352,"end":153.752},{"word":"of","start":153.752,"end":154.012},{"word":"idols,","start":154.012,"end":154.392},{"word":"from","start":154.852,"end":155.212},{"word":"sexual","start":155.212,"end":155.672},{"word":"immorality,","start":155.672,"end":156.532},{"word":"from","start":157.092,"end":157.232},{"word":"what","start":157.232,"end":157.432},{"word":"is","start":157.432,"end":157.632},{"word":"strangled,","start":157.632,"end":158.372},{"word":"and","start":158.372,"end":158.652},{"word":"from","start":158.652,"end":158.852},{"word":"blood.","start":158.852,"end":159.152}]},{"verse":21,"start":159.358,"end":167.685,"words":[{"word":"For","start":159.598,"end":160.078},{"word":"Moses","start":160.078,"end":160.418},{"word":"from","start":160.418,"end":160.758},{"word":"generations","start":160.758,"end":161.338},{"word":"of","start":161.338,"end":161.698},{"word":"old","start":161.698,"end":162.038},{"word":"has","start":162.038,"end":162.698},{"word":"in","start":162.698,"end":162.878},{"word":"every","start":162.878,"end":163.138},{"word":"city","start":163.138,"end":163.438},{"word":"those","start":163.438,"end":163.738},{"word":"who","start":163.738,"end":163.998},{"word":"preach","start":163.998,"end":164.278},{"word":"him,","start":164.278,"end":164.618},{"word":"being","start":164.618,"end":165.458},{"word":"read","start":165.458,"end":165.798},{"word":"in","start":165.798,"end":166.018},{"word":"the","start":166.018,"end":166.118},{"word":"synagogues","start":166.118,"end":166.758},{"word":"every","start":166.758,"end":166.998},{"word":"Sabbath.\"","start":166.998,"end":167.358}]},{"verse":22,"start":167.685,"end":183.577,"words":[{"word":"Then","start":167.925,"end":168.425},{"word":"it","start":168.485,"end":168.585},{"word":"seemed","start":168.585,"end":168.905},{"word":"good","start":168.905,"end":169.205},{"word":"to","start":169.205,"end":169.405},{"word":"the","start":169.405,"end":169.545},{"word":"apostles","start":169.545,"end":169.925},{"word":"and","start":169.925,"end":170.285},{"word":"the","start":170.285,"end":170.425},{"word":"elders,","start":170.425,"end":170.765},{"word":"with","start":171.285,"end":171.625},{"word":"the","start":171.625,"end":171.765},{"word":"whole","start":171.765,"end":171.985},{"word":"assembly,","start":171.985,"end":172.485},{"word":"to","start":173.225,"end":173.345},{"word":"choose","start":173.345,"end":173.665},{"word":"men","start":173.665,"end":174.005},{"word":"out","start":174.005,"end":174.265},{"word":"of","start":174.265,"end":174.405},{"word":"their","start":174.405,"end":174.565},{"word":"company,","start":174.565,"end":175.025},{"word":"and","start":175.625,"end":175.845},{"word":"send","start":175.845,"end":176.065},{"word":"them","start":176.065,"end":176.225},{"word":"to","start":176.225,"end":176.385},{"word":"Antioch","start":176.385,"end":177.045},{"word":"with","start":177.045,"end":177.165},{"word":"Paul","start":177.165,"end":177.505},{"word":"and","start":177.505,"end":177.725},{"word":"Barnabas:","start":177.725,"end":178.345},{"word":"Judas","start":178.885,"end":179.145},{"word":"called","start":179.145,"end":179.645},{"word":"Barsabbas,","start":179.645,"end":180.485},{"word":"and","start":180.485,"end":180.965},{"word":"Silas,","start":180.965,"end":181.565},{"word":"chief","start":181.905,"end":182.225},{"word":"men","start":182.225,"end":182.505},{"word":"among","start":182.505,"end":182.785},{"word":"the","start":182.785,"end":183.005},{"word":"brothers.","start":183.005,"end":183.265}]},{"verse":23,"start":183.577,"end":186.215,"words":[{"word":"They","start":183.817,"end":184.277},{"word":"wrote","start":184.277,"end":184.517},{"word":"these","start":184.517,"end":184.797},{"word":"things","start":184.797,"end":185.157},{"word":"by","start":185.157,"end":185.437},{"word":"their","start":185.437,"end":185.637},{"word":"hand:","start":185.637,"end":185.937}]},{"verse":24,"start":186.215,"end":199.76,"words":[{"word":"Because","start":186.515,"end":187.075},{"word":"we","start":187.075,"end":187.295},{"word":"have","start":187.295,"end":187.495},{"word":"heard","start":187.495,"end":187.815},{"word":"that","start":187.815,"end":188.055},{"word":"some","start":188.055,"end":188.395},{"word":"who","start":188.395,"end":188.635},{"word":"went","start":188.635,"end":188.875},{"word":"out","start":188.875,"end":189.135},{"word":"from","start":189.135,"end":189.395},{"word":"us","start":189.395,"end":189.595},{"word":"have","start":189.595,"end":189.795},{"word":"troubled","start":189.795,"end":190.215},{"word":"you","start":190.215,"end":190.475},{"word":"with","start":190.475,"end":190.655},{"word":"words,","start":190.655,"end":191.155},{"word":"unsettling","start":192.015,"end":192.535},{"word":"your","start":192.535,"end":192.735},{"word":"souls,","start":192.735,"end":193.195},{"word":"saying,","start":193.635,"end":194.015},{"word":"'You","start":194.015,"end":194.975},{"word":"must","start":194.975,"end":195.235},{"word":"be","start":195.235,"end":195.435},{"word":"circumcised","start":195.435,"end":196.335},{"word":"and","start":196.335,"end":196.535},{"word":"keep","start":196.535,"end":196.735},{"word":"the","start":196.735,"end":196.935},{"word":"law,'","start":196.935,"end":197.855},{"word":"to","start":197.855,"end":198.075},{"word":"whom","start":198.075,"end":198.275},{"word":"we","start":198.275,"end":198.475},{"word":"gave","start":198.475,"end":198.635},{"word":"no","start":198.635,"end":198.915},{"word":"commandment;","start":198.915,"end":199.655}]},{"verse":25,"start":199.76,"end":208.88,"words":[{"word":"it","start":199.97,"end":200.47},{"word":"seemed","start":200.47,"end":200.77},{"word":"good","start":200.77,"end":201.01},{"word":"to","start":201.01,"end":201.23},{"word":"us,","start":201.23,"end":201.55},{"word":"having","start":201.99,"end":202.17},{"word":"come","start":202.17,"end":202.51},{"word":"to","start":202.51,"end":202.69},{"word":"one","start":202.69,"end":202.89},{"word":"accord,","start":202.89,"end":203.29},{"word":"to","start":203.83,"end":203.99},{"word":"choose","start":203.99,"end":204.27},{"word":"out","start":204.27,"end":204.59},{"word":"men","start":204.59,"end":204.89},{"word":"and","start":204.89,"end":205.25},{"word":"send","start":205.25,"end":205.53},{"word":"them","start":205.53,"end":205.77},{"word":"to","start":205.77,"end":205.99},{"word":"you","start":205.99,"end":206.25},{"word":"with","start":206.25,"end":206.59},{"word":"our","start":206.59,"end":206.77},{"word":"beloved","start":206.77,"end":207.27},{"word":"Barnabas","start":207.27,"end":208.15},{"word":"and","start":208.15,"end":208.33},{"word":"Paul,","start":208.33,"end":208.65}]},{"verse":26,"start":208.88,"end":213.503,"words":[{"word":"men","start":209.5,"end":209.7},{"word":"who","start":209.7,"end":209.96},{"word":"have","start":209.96,"end":210.16},{"word":"risked","start":210.16,"end":210.56},{"word":"their","start":210.56,"end":210.66},{"word":"lives","start":210.66,"end":211.02},{"word":"for","start":211.02,"end":211.22},{"word":"the","start":211.22,"end":211.3},{"word":"name","start":211.3,"end":211.54},{"word":"of","start":211.54,"end":211.74},{"word":"our","start":211.74,"end":211.88},{"word":"Lord","start":211.88,"end":212.18},{"word":"Jesus","start":212.18,"end":212.58},{"word":"Christ.","start":212.58,"end":213.14}]},{"verse":27,"start":213.503,"end":221.392,"words":[{"word":"We","start":213.873,"end":214.193},{"word":"have","start":214.193,"end":214.353},{"word":"sent","start":214.353,"end":214.653},{"word":"therefore","start":214.653,"end":215.133},{"word":"Judas","start":215.133,"end":215.613},{"word":"and","start":215.613,"end":216.013},{"word":"Silas,","start":216.013,"end":216.673},{"word":"who","start":217.113,"end":217.433},{"word":"themselves","start":217.433,"end":217.893},{"word":"will","start":217.893,"end":218.273},{"word":"also","start":218.273,"end":218.653},{"word":"tell","start":218.653,"end":218.933},{"word":"you","start":218.933,"end":219.153},{"word":"the","start":219.153,"end":219.313},{"word":"same","start":219.313,"end":219.613},{"word":"things","start":219.613,"end":220.013},{"word":"by","start":220.013,"end":220.373},{"word":"word","start":220.373,"end":220.713},{"word":"of","start":220.713,"end":220.873},{"word":"mouth.","start":220.873,"end":221.133}]},{"verse":28,"start":221.392,"end":229.403,"words":[{"word":"For","start":221.662,"end":222.202},{"word":"it","start":222.202,"end":222.422},{"word":"seemed","start":222.422,"end":222.742},{"word":"good","start":222.742,"end":223.102},{"word":"to","start":223.102,"end":223.382},{"word":"the","start":223.382,"end":223.522},{"word":"Holy","start":223.522,"end":223.762},{"word":"Spirit,","start":223.762,"end":224.242},{"word":"and","start":224.242,"end":224.762},{"word":"to","start":224.762,"end":224.962},{"word":"us,","start":224.962,"end":225.222},{"word":"to","start":225.222,"end":225.942},{"word":"lay","start":225.942,"end":226.162},{"word":"no","start":226.162,"end":226.442},{"word":"greater","start":226.442,"end":226.762},{"word":"burden","start":226.762,"end":227.142},{"word":"on","start":227.142,"end":227.422},{"word":"you","start":227.422,"end":227.642},{"word":"than","start":227.642,"end":227.862},{"word":"these","start":227.862,"end":228.102},{"word":"necessary","start":228.102,"end":228.742},{"word":"things:","start":228.742,"end":229.102}]},{"verse":29,"start":229.403,"end":242.765,"words":[{"word":"that","start":229.803,"end":230.163},{"word":"you","start":230.163,"end":230.303},{"word":"abstain","start":230.303,"end":230.863},{"word":"from","start":230.863,"end":231.043},{"word":"things","start":231.043,"end":231.323},{"word":"sacrificed","start":231.323,"end":231.903},{"word":"to","start":231.903,"end":232.283},{"word":"idols,","start":232.283,"end":232.703},{"word":"from","start":233.183,"end":233.363},{"word":"blood,","start":233.363,"end":233.743},{"word":"from","start":234.483,"end":234.683},{"word":"things","start":234.683,"end":234.963},{"word":"strangled,","start":234.963,"end":235.603},{"word":"and","start":236.243,"end":236.423},{"word":"from","start":236.423,"end":236.623},{"word":"sexual","start":236.623,"end":237.023},{"word":"immorality,","start":237.023,"end":237.803},{"word":"from","start":238.343,"end":238.523},{"word":"which","start":238.523,"end":238.763},{"word":"if","start":238.763,"end":238.983},{"word":"you","start":238.983,"end":239.103},{"word":"keep","start":239.103,"end":239.323},{"word":"yourselves,","start":239.323,"end":239.903},{"word":"it","start":240.423,"end":240.523},{"word":"will","start":240.523,"end":240.683},{"word":"be","start":240.683,"end":240.843},{"word":"well","start":240.843,"end":241.143},{"word":"with","start":241.143,"end":241.383},{"word":"you.","start":241.383,"end":241.623},{"word":"Farewell.\"","start":242.143,"end":242.623}]},{"verse":30,"start":242.765,"end":251.009,"words":[{"word":"So,","start":243.105,"end":243.685},{"word":"when","start":243.685,"end":244.405},{"word":"they","start":244.405,"end":244.545},{"word":"were","start":244.545,"end":244.685},{"word":"sent","start":244.685,"end":244.865},{"word":"off,","start":244.865,"end":245.185},{"word":"they","start":245.185,"end":245.545},{"word":"came","start":245.545,"end":245.845},{"word":"to","start":245.845,"end":246.065},{"word":"Antioch.","start":246.065,"end":246.845},{"word":"Having","start":246.845,"end":247.565},{"word":"gathered","start":247.565,"end":247.985},{"word":"the","start":247.985,"end":248.165},{"word":"multitude","start":248.165,"end":248.485},{"word":"together,","start":248.485,"end":249.085},{"word":"they","start":249.085,"end":249.965},{"word":"delivered","start":249.965,"end":250.345},{"word":"the","start":250.345,"end":250.585},{"word":"letter.","start":250.585,"end":250.805}]},{"verse":31,"start":251.009,"end":255.365,"words":[{"word":"When","start":251.569,"end":251.729},{"word":"they","start":251.729,"end":251.929},{"word":"had","start":251.929,"end":252.069},{"word":"read","start":252.069,"end":252.269},{"word":"it,","start":252.269,"end":252.529},{"word":"they","start":253.109,"end":253.249},{"word":"rejoiced","start":253.249,"end":253.969},{"word":"over","start":253.969,"end":254.229},{"word":"the","start":254.229,"end":254.389},{"word":"encouragement.","start":254.389,"end":254.809}]},{"verse":32,"start":255.365,"end":263.053,"words":[{"word":"Judas","start":255.635,"end":256.235},{"word":"and","start":256.235,"end":256.635},{"word":"Silas,","start":256.635,"end":257.255},{"word":"also","start":257.535,"end":257.815},{"word":"being","start":257.815,"end":258.135},{"word":"prophets","start":258.135,"end":258.515},{"word":"themselves,","start":258.515,"end":259.155},{"word":"encouraged","start":259.775,"end":260.255},{"word":"the","start":260.255,"end":260.595},{"word":"brothers","start":260.595,"end":260.895},{"word":"with","start":260.895,"end":261.215},{"word":"many","start":261.215,"end":261.495},{"word":"words","start":261.495,"end":261.875},{"word":"and","start":261.875,"end":262.215},{"word":"strengthened","start":262.215,"end":262.635},{"word":"them.","start":262.635,"end":262.955}]},{"verse":33,"start":263.053,"end":270.238,"words":[{"word":"After","start":263.513,"end":263.933},{"word":"they","start":263.933,"end":264.153},{"word":"had","start":264.153,"end":264.373},{"word":"spent","start":264.373,"end":264.633},{"word":"some","start":264.633,"end":264.913},{"word":"time","start":264.913,"end":265.253},{"word":"there,","start":265.253,"end":265.693},{"word":"they","start":266.193,"end":266.493},{"word":"were","start":266.493,"end":266.613},{"word":"dismissed","start":266.613,"end":267.173},{"word":"in","start":267.173,"end":267.533},{"word":"peace","start":267.533,"end":267.873},{"word":"from","start":267.873,"end":268.353},{"word":"the","start":268.353,"end":268.513},{"word":"brothers","start":268.513,"end":268.853},{"word":"to","start":268.853,"end":269.293},{"word":"the","start":269.293,"end":269.413},{"word":"apostles.","start":269.413,"end":269.753}]}]}