{"book":"Jeremiah","abbr":"JER","slug":"jeremiah","chapter":6,"totalChapters":52,"verses":[{"number":1,"words":[{"text":"“Flee","s":"H5756"},{"text":"for","s":"H3588"},{"text":"safety,","s":"H5756"},{"text":"you","s":"H3588"},{"text":"children","s":"H1121"},{"text":"of","s":"H1121"},{"text":"Benjamin,","s":"H1144"},{"text":"out","s":"H8259"},{"text":"of","s":"H1121"},{"text":"the","s":"H5921"},{"text":"middle","s":"H7130"},{"text":"of","s":"H1121"},{"text":"Jerusalem!","s":"H3389"},{"text":"Blow","s":"H8628"},{"text":"the","s":"H5921"},{"text":"trumpet","s":"H7782"},{"text":"in","s":"H5921"},{"text":"Tekoa","s":"H8620"},{"text":"and","s":"H1121"},{"text":"raise","s":"H5375"},{"text":"up","s":"H5375"},{"text":"a","s":"H3068"},{"text":"signal","s":"H4864"},{"text":"on","s":"H5921"},{"text":"Beth"},{"text":"Haccherem,"},{"text":"for","s":"H3588"},{"text":"evil","s":"H7451"},{"text":"looks","s":"H8259"},{"text":"out","s":"H8259"},{"text":"from","s":"H5921"},{"text":"the","s":"H5921"},{"text":"north","s":"H6828"},{"text":"with","s":"H5921"},{"text":"a","s":"H3068"},{"text":"great","s":"H1419"},{"text":"destruction.","s":"H7667"}],"paragraphStart":true},{"number":2,"words":[{"text":"I"},{"text":"will","s":"H1323"},{"text":"cut","s":"H1820"},{"text":"off","s":"H1820"},{"text":"the","s":"H6726"},{"text":"beautiful"},{"text":"and","s":"H1323"},{"text":"delicate","s":"H6026"},{"text":"one,"},{"text":"the","s":"H6726"},{"text":"daughter","s":"H1323"},{"text":"of","s":"H1323"},{"text":"Zion.","s":"H6726"}]},{"number":3,"words":[{"text":"Shepherds","s":"H7462"},{"text":"with","s":"H5921"},{"text":"their","s":"H5921"},{"text":"flocks","s":"H5739"},{"text":"will","s":"H3027"},{"text":"come"},{"text":"to","s":"H5921"},{"text":"her.","s":"H5921"},{"text":"They","s":"H5921"},{"text":"will","s":"H3027"},{"text":"pitch","s":"H8628"},{"text":"their","s":"H5921"},{"text":"tents"},{"text":"against","s":"H5921"},{"text":"her","s":"H5921"},{"text":"all","s":"H5439"},{"text":"around.","s":"H5439"},{"text":"They","s":"H5921"},{"text":"will","s":"H3027"},{"text":"feed","s":"H7462"},{"text":"everyone"},{"text":"in","s":"H5921"},{"text":"his","s":"H5921"},{"text":"place.”","s":"H3027"},{"break":true}]},{"number":4,"words":[{"text":"“Prepare","s":"H6942"},{"text":"war","s":"H4421"},{"text":"against","s":"H5921"},{"text":"her!","s":"H5921"},{"text":"Arise!","s":"H6965"},{"text":"Let's","s":"H5186"},{"text":"go","s":"H5927"},{"text":"up","s":"H5927"},{"text":"at","s":"H5921"},{"text":"noon.","s":"H6672"},{"text":"Woe"},{"text":"to","s":"H5927"},{"text":"us!","s":"H5921"},{"text":"For","s":"H3588"},{"text":"the","s":"H5921"},{"text":"day","s":"H3117"},{"text":"declines,","s":"H6437"},{"text":"for","s":"H3588"},{"text":"the","s":"H5921"},{"text":"shadows","s":"H6752"},{"text":"of","s":"H3117"},{"text":"the","s":"H5921"},{"text":"evening","s":"H6153"},{"text":"are","s":"H3117"},{"text":"stretched","s":"H5186"},{"text":"out.","s":"H5186"}],"paragraphStart":true},{"number":5,"words":[{"text":"Arise!","s":"H6965"},{"text":"Let’s"},{"text":"go","s":"H5927"},{"text":"up","s":"H5927"},{"text":"by","s":"H6965"},{"text":"night,","s":"H3915"},{"text":"and","s":"H6965"},{"text":"let’s"},{"text":"destroy","s":"H7843"},{"text":"her","s":"H7843"},{"text":"palaces.”"}]},{"number":6,"words":[{"text":"For","s":"H3588"},{"text":"Yahweh","s":"H3068"},{"text":"of","s":"H3068"},{"text":"Armies","s":"H6635"},{"text":"said,"},{"text":"“Cut","s":"H3772"},{"text":"down","s":"H3772"},{"text":"trees,","s":"H6097"},{"text":"and","s":"H3068"},{"text":"cast","s":"H8210"},{"text":"up","s":"H5921"},{"text":"a","s":"H3068"},{"text":"mound"},{"text":"against","s":"H5921"},{"text":"Jerusalem.","s":"H3389"},{"text":"This","s":"H1931"},{"text":"is","s":"H3068"},{"text":"the","s":"H3605"},{"text":"city","s":"H5892"},{"text":"to","s":"H3068"},{"text":"be","s":"H3068"},{"text":"visited.","s":"H6485"},{"text":"She","s":"H1931"},{"text":"is","s":"H3068"},{"text":"filled"},{"text":"with","s":"H3068"},{"text":"oppression","s":"H6233"},{"text":"within","s":"H7130"},{"text":"herself.","s":"H1931"}]},{"number":7,"words":[{"text":"As","s":"H3651"},{"text":"a","s":"H3068"},{"text":"well","s":"H3651"},{"text":"produces"},{"text":"its","s":"H5921"},{"text":"waters,","s":"H4325"},{"text":"so","s":"H3651"},{"text":"she","s":"H5921"},{"text":"produces"},{"text":"her","s":"H5921"},{"text":"wickedness.","s":"H7451"},{"text":"Violence","s":"H2555"},{"text":"and","s":"H6440"},{"text":"destruction","s":"H7701"},{"text":"is","s":"H3651"},{"text":"heard","s":"H8085"},{"text":"in","s":"H5921"},{"text":"her.","s":"H5921"},{"text":"Sickness","s":"H2483"},{"text":"and","s":"H6440"},{"text":"wounds","s":"H4347"},{"text":"are","s":"H4325"},{"text":"continually","s":"H8548"},{"text":"before","s":"H6440"},{"text":"me.","s":"H6440"}]},{"number":8,"words":[{"text":"Be","s":"H3808"},{"text":"instructed,","s":"H3256"},{"text":"Jerusalem,","s":"H3389"},{"text":"lest","s":"H6435"},{"text":"my","s":"H7760"},{"text":"soul","s":"H5315"},{"text":"be","s":"H3808"},{"text":"alienated","s":"H3363"},{"text":"from","s":"H4480"},{"text":"you,","s":"H7760"},{"text":"lest","s":"H6435"},{"text":"I","s":"H7760"},{"text":"make","s":"H7760"},{"text":"you","s":"H7760"},{"text":"a","s":"H3068"},{"text":"desolation,","s":"H8077"},{"text":"an","s":"H7760"},{"text":"uninhabited","s":"H8077"},{"text":"land.”"},{"break":true}]},{"number":9,"words":[{"text":"Yahweh","s":"H3068"},{"text":"of","s":"H3068"},{"text":"Armies","s":"H6635"},{"text":"says,","s":"H3541"},{"text":"“They","s":"H3068"},{"text":"will","s":"H3068"},{"text":"thoroughly","s":"H5953"},{"text":"glean","s":"H5953"},{"text":"the","s":"H5921"},{"text":"remnant","s":"H7611"},{"text":"of","s":"H3068"},{"text":"Israel","s":"H3478"},{"text":"like","s":"H3478"},{"text":"a","s":"H3068"},{"text":"vine.","s":"H1612"},{"text":"Turn","s":"H7725"},{"text":"again","s":"H7725"},{"text":"your","s":"H3068"},{"text":"hand","s":"H3027"},{"text":"as","s":"H3068"},{"text":"a","s":"H3068"},{"text":"grape"},{"text":"gatherer","s":"H1219"},{"text":"into","s":"H7725"},{"text":"the","s":"H5921"},{"text":"baskets.”","s":"H5552"},{"break":true}],"paragraphStart":true},{"number":10,"words":[{"text":"To","s":"H1696"},{"text":"whom","s":"H4310"},{"text":"should","s":"H3068"},{"text":"I","s":"H2009"},{"text":"speak","s":"H1696"},{"text":"and","s":"H3068"},{"text":"testify,","s":"H5749"},{"text":"that","s":"H8085"},{"text":"they","s":"H3068"},{"text":"may","s":"H1961"},{"text":"hear?","s":"H8085"},{"text":"Behold,","s":"H2009"},{"text":"their","s":"H3068"},{"text":"ear","s":"H8085"},{"text":"is","s":"H3068"},{"text":"uncircumcised,","s":"H6189"},{"text":"and","s":"H3068"},{"text":"they","s":"H3068"},{"text":"can","s":"H4310"},{"text":"’t"},{"text":"listen.","s":"H8085"},{"text":"Behold,","s":"H2009"},{"text":"Yahweh's","s":"H3068"},{"text":"word","s":"H1697"},{"text":"has","s":"H3068"},{"text":"become","s":"H1961"},{"text":"a","s":"H3068"},{"text":"reproach","s":"H2781"},{"text":"to","s":"H1696"},{"text":"them.","s":"H5921"},{"text":"They","s":"H3068"},{"text":"have","s":"H1961"},{"text":"no","s":"H3808"},{"text":"delight","s":"H2654"},{"text":"in","s":"H5921"},{"text":"it.","s":"H5921"}],"paragraphStart":true},{"number":11,"words":[{"text":"Therefore","s":"H5921"},{"text":"I","s":"H3588"},{"text":"am","s":"H3068"},{"text":"full","s":"H4392"},{"text":"of","s":"H3068"},{"text":"Yahweh's","s":"H3068"},{"text":"wrath.","s":"H2534"},{"text":"I","s":"H3588"},{"text":"am","s":"H3068"},{"text":"weary","s":"H3811"},{"text":"with","s":"H5973"},{"text":"holding","s":"H3557"},{"text":"it","s":"H5921"},{"text":"in.","s":"H5921"},{"text":"“Pour","s":"H8210"},{"text":"it","s":"H5921"},{"text":"out","s":"H8210"},{"text":"on","s":"H5921"},{"text":"the","s":"H5921"},{"text":"children","s":"H5768"},{"text":"in","s":"H5921"},{"text":"the","s":"H5921"},{"text":"street,","s":"H2351"},{"text":"and","s":"H3068"},{"text":"on","s":"H5921"},{"text":"the","s":"H5921"},{"text":"assembly","s":"H5475"},{"text":"of","s":"H3068"},{"text":"young","s":"H3117"},{"text":"men","s":"H2205"},{"text":"together;","s":"H3162"},{"text":"for","s":"H3588"},{"text":"even","s":"H1571"},{"text":"the","s":"H5921"},{"text":"husband"},{"text":"with","s":"H5973"},{"text":"the","s":"H5921"},{"text":"wife"},{"text":"will","s":"H3068"},{"text":"be","s":"H3068"},{"text":"taken,","s":"H3920"},{"text":"the","s":"H5921"},{"text":"aged","s":"H2205"},{"text":"with","s":"H5973"},{"text":"him","s":"H5921"},{"text":"who","s":"H3068"},{"text":"is","s":"H3068"},{"text":"full","s":"H4392"},{"text":"of","s":"H3068"},{"text":"days.","s":"H3117"}]},{"number":12,"words":[{"text":"Their","s":"H3068"},{"text":"houses","s":"H1004"},{"text":"will","s":"H3068"},{"text":"be","s":"H3027"},{"text":"turned","s":"H5437"},{"text":"to","s":"H3068"},{"text":"others,"},{"text":"their","s":"H3068"},{"text":"fields","s":"H7704"},{"text":"and","s":"H3068"},{"text":"their","s":"H3068"},{"text":"wives"},{"text":"together;","s":"H3162"},{"text":"for","s":"H3588"},{"text":"I","s":"H3588"},{"text":"will","s":"H3068"},{"text":"stretch","s":"H5186"},{"text":"out","s":"H5186"},{"text":"my","s":"H3068"},{"text":"hand","s":"H3027"},{"text":"on","s":"H5921"},{"text":"the","s":"H5002"},{"text":"inhabitants","s":"H3427"},{"text":"of","s":"H1004"},{"text":"the","s":"H5002"},{"text":"land,","s":"H7704"},{"text":"says","s":"H5002"},{"text":"Yahweh.”","s":"H3068"}]},{"number":13,"words":[{"text":"“For","s":"H3588"},{"text":"from","s":"H5704"},{"text":"their","s":"H3605"},{"text":"least","s":"H6996"},{"text":"even","s":"H5704"},{"text":"to","s":"H5704"},{"text":"their","s":"H3605"},{"text":"greatest,","s":"H1419"},{"text":"everyone","s":"H3605"},{"text":"is","s":"H3605"},{"text":"given","s":"H1214"},{"text":"to","s":"H5704"},{"text":"covetousness.","s":"H1215"},{"text":"From","s":"H5704"},{"text":"the","s":"H3605"},{"text":"prophet","s":"H5030"},{"text":"even","s":"H5704"},{"text":"to","s":"H5704"},{"text":"the","s":"H3605"},{"text":"priest,","s":"H3548"},{"text":"everyone","s":"H3605"},{"text":"deals","s":"H6213"},{"text":"falsely.","s":"H8267"}]},{"number":14,"words":[{"text":"They","s":"H5921"},{"text":"have","s":"H5971"},{"text":"healed","s":"H7495"},{"text":"also","s":"H5971"},{"text":"the","s":"H5921"},{"text":"hurt","s":"H7667"},{"text":"of","s":"H5971"},{"text":"my","s":"H5921"},{"text":"people","s":"H5971"},{"text":"superficially,","s":"H7043"},{"text":"saying,"},{"text":"‘Peace,","s":"H7965"},{"text":"peace!’","s":"H7965"},{"text":"when","s":"H5921"},{"text":"there","s":"H7965"},{"text":"is","s":"H5971"},{"text":"no"},{"text":"peace.","s":"H7965"}]},{"number":15,"words":[{"text":"Were","s":"H6485"},{"text":"they","s":"H3588"},{"text":"ashamed","s":"H3637"},{"text":"when","s":"H3588"},{"text":"they","s":"H3588"},{"text":"had","s":"H3068"},{"text":"committed","s":"H6213"},{"text":"abomination?","s":"H8441"},{"text":"No,","s":"H3808"},{"text":"they","s":"H3588"},{"text":"were","s":"H6485"},{"text":"not","s":"H3808"},{"text":"at","s":"H3068"},{"text":"all","s":"H3045"},{"text":"ashamed,","s":"H3637"},{"text":"neither","s":"H3808"},{"text":"could","s":"H1571"},{"text":"they","s":"H3588"},{"text":"blush.","s":"H3637"},{"text":"Therefore","s":"H3651"},{"text":"they","s":"H3588"},{"text":"will","s":"H3068"},{"text":"fall","s":"H5307"},{"text":"among","s":"H3808"},{"text":"those","s":"H6213"},{"text":"who","s":"H3068"},{"text":"fall.","s":"H5307"},{"text":"When","s":"H3588"},{"text":"I","s":"H3588"},{"text":"visit","s":"H6485"},{"text":"them,","s":"H6213"},{"text":"they","s":"H3588"},{"text":"will","s":"H3068"},{"text":"be","s":"H3808"},{"text":"cast","s":"H5307"},{"text":"down,”","s":"H5307"},{"text":"says"},{"text":"Yahweh.","s":"H3068"},{"break":true}]},{"number":16,"words":[{"text":"Yahweh","s":"H3068"},{"text":"says,","s":"H3541"},{"text":"“Stand","s":"H5975"},{"text":"in","s":"H5921"},{"text":"the","s":"H5921"},{"text":"ways","s":"H1870"},{"text":"and","s":"H3068"},{"text":"see,","s":"H7200"},{"text":"and","s":"H3068"},{"text":"ask","s":"H7592"},{"text":"for","s":"H5921"},{"text":"the","s":"H5921"},{"text":"old","s":"H5769"},{"text":"paths,","s":"H5410"},{"text":"‘Where","s":"H5921"},{"text":"is","s":"H3068"},{"text":"the","s":"H5921"},{"text":"good","s":"H2896"},{"text":"way?’","s":"H1870"},{"text":"and","s":"H3068"},{"text":"walk","s":"H3212"},{"text":"in","s":"H5921"},{"text":"it,","s":"H5921"},{"text":"and","s":"H3068"},{"text":"you","s":"H5921"},{"text":"will","s":"H3068"},{"text":"find","s":"H4672"},{"text":"rest","s":"H4771"},{"text":"for","s":"H5921"},{"text":"your","s":"H3068"},{"text":"souls.","s":"H5315"},{"text":"But","s":"H3808"},{"text":"they","s":"H3068"},{"text":"said,"},{"text":"‘We","s":"H5315"},{"text":"will","s":"H3068"},{"text":"not","s":"H3808"},{"text":"walk","s":"H3212"},{"text":"in","s":"H5921"},{"text":"it.’","s":"H5921"}],"paragraphStart":true},{"number":17,"words":[{"text":"I","s":"H5921"},{"text":"set","s":"H6965"},{"text":"watchmen","s":"H6822"},{"text":"over","s":"H5921"},{"text":"you,","s":"H5921"},{"text":"saying,","s":"H6963"},{"text":"‘Listen","s":"H7181"},{"text":"to","s":"H5921"},{"text":"the","s":"H5921"},{"text":"sound","s":"H6963"},{"text":"of","s":"H6963"},{"text":"the","s":"H5921"},{"text":"trumpet!’","s":"H7782"},{"text":"But","s":"H3808"},{"text":"they","s":"H3808"},{"text":"said,"},{"text":"‘We"},{"text":"will","s":"H3808"},{"text":"not","s":"H3808"},{"text":"listen!’","s":"H7181"}]},{"number":18,"words":[{"text":"Therefore","s":"H3651"},{"text":"hear,","s":"H8085"},{"text":"you","s":"H3045"},{"text":"nations,","s":"H1471"},{"text":"and","s":"H8085"},{"text":"know,","s":"H3045"},{"text":"congregation,","s":"H5712"},{"text":"what","s":"H3045"},{"text":"is","s":"H3651"},{"text":"among"},{"text":"them.","s":"H8085"}]},{"number":19,"words":[{"text":"Hear,","s":"H8085"},{"text":"earth!"},{"text":"Behold,","s":"H2009"},{"text":"I","s":"H3588"},{"text":"will","s":"H5971"},{"text":"bring","s":"H7451"},{"text":"evil","s":"H7451"},{"text":"on","s":"H5921"},{"text":"this","s":"H2088"},{"text":"people,","s":"H5971"},{"text":"even","s":"H3588"},{"text":"the","s":"H5921"},{"text":"fruit","s":"H6529"},{"text":"of","s":"H1697"},{"text":"their","s":"H8085"},{"text":"thoughts,","s":"H4284"},{"text":"because","s":"H3588"},{"text":"they","s":"H3588"},{"text":"have","s":"H5971"},{"text":"not","s":"H3808"},{"text":"listened","s":"H8085"},{"text":"to","s":"H5921"},{"text":"my","s":"H8085"},{"text":"words;","s":"H1697"},{"text":"and","s":"H5971"},{"text":"as","s":"H1697"},{"text":"for","s":"H3588"},{"text":"my","s":"H8085"},{"text":"law,","s":"H8451"},{"text":"they","s":"H3588"},{"text":"have","s":"H5971"},{"text":"rejected","s":"H3988"},{"text":"it.","s":"H5921"}]},{"number":20,"words":[{"text":"To","s":"H2896"},{"text":"what","s":"H4100"},{"text":"purpose","s":"H2088"},{"text":"does","s":"H4100"},{"text":"frankincense","s":"H3828"},{"text":"from","s":"H2896"},{"text":"Sheba","s":"H7614"},{"text":"come"},{"text":"to","s":"H2896"},{"text":"me,","s":"H3808"},{"text":"and","s":"H5930"},{"text":"the","s":"H3808"},{"text":"sweet","s":"H6149"},{"text":"cane","s":"H7070"},{"text":"from","s":"H2896"},{"text":"a","s":"H3068"},{"text":"far","s":"H4801"},{"text":"country?"},{"text":"Your","s":"H3808"},{"text":"burnt","s":"H5930"},{"text":"offerings","s":"H5930"},{"text":"are","s":"H4100"},{"text":"not","s":"H3808"},{"text":"acceptable,","s":"H7522"},{"text":"and","s":"H5930"},{"text":"your","s":"H3808"},{"text":"sacrifices","s":"H2077"},{"text":"are","s":"H4100"},{"text":"not","s":"H3808"},{"text":"pleasing","s":"H2896"},{"text":"to","s":"H2896"},{"text":"me.”","s":"H3808"},{"break":true}]},{"number":21,"words":[{"text":"Therefore","s":"H3651"},{"text":"Yahweh","s":"H3068"},{"text":"says,","s":"H3541"},{"text":"“Behold,","s":"H2005"},{"text":"I","s":"H2005"},{"text":"will","s":"H3068"},{"text":"lay","s":"H5414"},{"text":"stumbling","s":"H4383"},{"text":"blocks","s":"H4383"},{"text":"before","s":"H5971"},{"text":"this","s":"H2088"},{"text":"people.","s":"H5971"},{"text":"The","s":"H5414"},{"text":"fathers"},{"text":"and","s":"H1121"},{"text":"the","s":"H5414"},{"text":"sons","s":"H1121"},{"text":"together","s":"H3162"},{"text":"will","s":"H3068"},{"text":"stumble","s":"H3782"},{"text":"against","s":"H3068"},{"text":"them.","s":"H5414"},{"text":"The","s":"H5414"},{"text":"neighbor","s":"H7453"},{"text":"and","s":"H1121"},{"text":"his","s":"H5414"},{"text":"friend","s":"H7453"},{"text":"will","s":"H3068"},{"text":"perish.”"}],"paragraphStart":true},{"number":22,"words":[{"text":"Yahweh","s":"H3068"},{"text":"says,","s":"H3541"},{"text":"“Behold,","s":"H2009"},{"text":"a","s":"H3068"},{"text":"people","s":"H5971"},{"text":"comes"},{"text":"from","s":"H1471"},{"text":"the","s":"H3541"},{"text":"north","s":"H6828"},{"text":"country."},{"text":"A","s":"H3068"},{"text":"great","s":"H1419"},{"text":"nation","s":"H1471"},{"text":"will","s":"H3068"},{"text":"be","s":"H3068"},{"text":"stirred","s":"H5782"},{"text":"up","s":"H5782"},{"text":"from","s":"H1471"},{"text":"the","s":"H3541"},{"text":"uttermost"},{"text":"parts","s":"H3411"},{"text":"of","s":"H3068"},{"text":"the","s":"H3541"},{"text":"earth."}]},{"number":23,"words":[{"text":"They","s":"H3808"},{"text":"take","s":"H2388"},{"text":"hold","s":"H2388"},{"text":"of","s":"H1323"},{"text":"bow","s":"H7198"},{"text":"and","s":"H6963"},{"text":"spear.","s":"H3591"},{"text":"They","s":"H3808"},{"text":"are","s":"H6726"},{"text":"cruel,"},{"text":"and","s":"H6963"},{"text":"have","s":"H7355"},{"text":"no","s":"H3808"},{"text":"mercy.","s":"H7355"},{"text":"Their","s":"H5921"},{"text":"voice","s":"H6963"},{"text":"roars","s":"H1993"},{"text":"like","s":"H1993"},{"text":"the","s":"H5921"},{"text":"sea,","s":"H3220"},{"text":"and","s":"H6963"},{"text":"they","s":"H3808"},{"text":"ride","s":"H7392"},{"text":"on","s":"H5921"},{"text":"horses,","s":"H5483"},{"text":"everyone"},{"text":"set","s":"H6186"},{"text":"in","s":"H5921"},{"text":"array,","s":"H6186"},{"text":"as","s":"H1323"},{"text":"a","s":"H3068"},{"text":"man"},{"text":"to","s":"H5921"},{"text":"the","s":"H5921"},{"text":"battle,","s":"H4421"},{"text":"against","s":"H5921"},{"text":"you,","s":"H5921"},{"text":"daughter","s":"H1323"},{"text":"of","s":"H1323"},{"text":"Zion.”","s":"H6726"},{"break":true}]},{"number":24,"words":[{"text":"We","s":"H8085"},{"text":"have","s":"H3027"},{"text":"heard","s":"H8085"},{"text":"its"},{"text":"report.","s":"H8089"},{"text":"Our","s":"H8085"},{"text":"hands","s":"H3027"},{"text":"become","s":"H3205"},{"text":"feeble.","s":"H7503"},{"text":"Anguish","s":"H6869"},{"text":"has","s":"H3027"},{"text":"taken","s":"H2388"},{"text":"hold","s":"H2388"},{"text":"of","s":"H3027"},{"text":"us,","s":"H8085"},{"text":"and","s":"H3027"},{"text":"pains"},{"text":"as","s":"H2388"},{"text":"of","s":"H3027"},{"text":"a","s":"H3068"},{"text":"woman","s":"H3205"},{"text":"in","s":"H8085"},{"text":"labor.","s":"H3205"}],"paragraphStart":true},{"number":25,"words":[{"text":"Don’t"},{"text":"go","s":"H3212"},{"text":"out","s":"H3318"},{"text":"into","s":"H3212"},{"text":"the","s":"H3588"},{"text":"field","s":"H7704"},{"text":"or","s":"H7704"},{"text":"walk","s":"H3212"},{"text":"by","s":"H1870"},{"text":"the","s":"H3588"},{"text":"way;","s":"H1870"},{"text":"for","s":"H3588"},{"text":"the","s":"H3588"},{"text":"sword","s":"H2719"},{"text":"of","s":"H1870"},{"text":"the","s":"H3588"},{"text":"enemy"},{"text":"and","s":"H3212"},{"text":"terror","s":"H4032"},{"text":"are","s":"H1870"},{"text":"on","s":"H1870"},{"text":"every","s":"H5439"},{"text":"side.","s":"H5439"}]},{"number":26,"words":[{"text":"Daughter","s":"H1323"},{"text":"of","s":"H1323"},{"text":"my","s":"H5921"},{"text":"people,","s":"H5971"},{"text":"clothe"},{"text":"yourself","s":"H6213"},{"text":"with","s":"H6213"},{"text":"sackcloth,","s":"H8242"},{"text":"and","s":"H5971"},{"text":"wallow","s":"H6428"},{"text":"in","s":"H5921"},{"text":"ashes!"},{"text":"Mourn,","s":"H5921"},{"text":"as","s":"H6213"},{"text":"for","s":"H3588"},{"text":"an","s":"H6213"},{"text":"only","s":"H3173"},{"text":"son,","s":"H3173"},{"text":"most","s":"H8563"},{"text":"bitter","s":"H8563"},{"text":"lamentation,","s":"H4553"},{"text":"for","s":"H3588"},{"text":"the","s":"H5921"},{"text":"destroyer","s":"H7703"},{"text":"will","s":"H5971"},{"text":"suddenly","s":"H6597"},{"text":"come","s":"H5971"},{"text":"on","s":"H5921"},{"text":"us.","s":"H5921"},{"break":true}]},{"number":27,"words":[{"text":"“I","s":"H5414"},{"text":"have","s":"H5971"},{"text":"made","s":"H5414"},{"text":"you","s":"H5414"},{"text":"a","s":"H3068"},{"text":"tester","s":"H4013"},{"text":"of","s":"H1870"},{"text":"metals"},{"text":"and","s":"H5971"},{"text":"a","s":"H3068"},{"text":"fortress","s":"H4013"},{"text":"among","s":"H5971"},{"text":"my","s":"H5414"},{"text":"people,","s":"H5971"},{"text":"that","s":"H3045"},{"text":"you","s":"H5414"},{"text":"may","s":"H5971"},{"text":"know","s":"H3045"},{"text":"and","s":"H5971"},{"text":"try"},{"text":"their","s":"H5414"},{"text":"way.","s":"H1870"}],"paragraphStart":true},{"number":28,"words":[{"text":"They","s":"H1992"},{"text":"are","s":"H1992"},{"text":"all","s":"H3605"},{"text":"grievous","s":"H5493"},{"text":"rebels,","s":"H5637"},{"text":"going","s":"H1980"},{"text":"around","s":"H1980"},{"text":"to","s":"H1980"},{"text":"slander."},{"text":"They","s":"H1992"},{"text":"are","s":"H1992"},{"text":"bronze","s":"H5178"},{"text":"and","s":"H1980"},{"text":"iron.","s":"H1270"},{"text":"All","s":"H3605"},{"text":"of","s":"H3605"},{"text":"them","s":"H1992"},{"text":"deal"},{"text":"corruptly.","s":"H7843"}]},{"number":29,"words":[{"text":"The","s":"H3808"},{"text":"bellows","s":"H4647"},{"text":"blow","s":"H2787"},{"text":"fiercely.","s":"H2787"},{"text":"The","s":"H3808"},{"text":"lead","s":"H5777"},{"text":"is","s":"H7451"},{"text":"consumed"},{"text":"in","s":"H3808"},{"text":"the","s":"H3808"},{"text":"fire."},{"text":"In","s":"H3808"},{"text":"vain","s":"H7723"},{"text":"they","s":"H3808"},{"text":"go"},{"text":"on","s":"H7451"},{"text":"refining,","s":"H6884"},{"text":"for","s":"H7451"},{"text":"the","s":"H3808"},{"text":"wicked","s":"H7451"},{"text":"are","s":"H4647"},{"text":"not","s":"H3808"},{"text":"plucked"},{"text":"away.","s":"H5423"}]},{"number":30,"words":[{"text":"Men","s":"H7121"},{"text":"will","s":"H3068"},{"text":"call","s":"H7121"},{"text":"them","s":"H7121"},{"text":"rejected","s":"H3988"},{"text":"silver,","s":"H3701"},{"text":"because","s":"H3588"},{"text":"Yahweh","s":"H3068"},{"text":"has","s":"H3068"},{"text":"rejected","s":"H3988"},{"text":"them.”","s":"H7121"}]}]}